gym_ignition_models/__init__.py
gym_ignition_models/cartpole/cartpole.urdf
gym_ignition_models/cartpole/model.config
gym_ignition_models/character/character.urdf
gym_ignition_models/character/model.config
gym_ignition_models/ground_plane/ground_plane.sdf
gym_ignition_models/ground_plane/model.config
gym_ignition_models/iCubGazeboSimpleCollisionsV2_5/icub_simple_collisions.urdf
gym_ignition_models/iCubGazeboSimpleCollisionsV2_5/model.config
gym_ignition_models/iCubGazeboSimpleCollisionsV2_5/meshes/simmechanics/sim_sea_2-5_chest_bb_prt-binary.stl
gym_ignition_models/iCubGazeboSimpleCollisionsV2_5/meshes/simmechanics/sim_sea_2-5_head_prt-binary.stl
gym_ignition_models/iCubGazeboSimpleCollisionsV2_5/meshes/simmechanics/sim_sea_2-5_l_ankle_prt-binary.stl
gym_ignition_models/iCubGazeboSimpleCollisionsV2_5/meshes/simmechanics/sim_sea_2-5_l_elbow_prosup_prt-binary.stl
gym_ignition_models/iCubGazeboSimpleCollisionsV2_5/meshes/simmechanics/sim_sea_2-5_l_elbow_prt-binary.stl
gym_ignition_models/iCubGazeboSimpleCollisionsV2_5/meshes/simmechanics/sim_sea_2-5_l_foot_prt-binary.stl
gym_ignition_models/iCubGazeboSimpleCollisionsV2_5/meshes/simmechanics/sim_sea_2-5_l_forearm_prt-binary.stl
gym_ignition_models/iCubGazeboSimpleCollisionsV2_5/meshes/simmechanics/sim_sea_2-5_l_hand_prt-binary.stl
gym_ignition_models/iCubGazeboSimpleCollisionsV2_5/meshes/simmechanics/sim_sea_2-5_l_hip_1_prt-binary.stl
gym_ignition_models/iCubGazeboSimpleCollisionsV2_5/meshes/simmechanics/sim_sea_2-5_l_hip_2_prt-binary.stl
gym_ignition_models/iCubGazeboSimpleCollisionsV2_5/meshes/simmechanics/sim_sea_2-5_l_shank_prt-binary.stl
gym_ignition_models/iCubGazeboSimpleCollisionsV2_5/meshes/simmechanics/sim_sea_2-5_l_shoulder_1_prt-binary.stl
gym_ignition_models/iCubGazeboSimpleCollisionsV2_5/meshes/simmechanics/sim_sea_2-5_l_shoulder_2_prt-binary.stl
gym_ignition_models/iCubGazeboSimpleCollisionsV2_5/meshes/simmechanics/sim_sea_2-5_l_sole_prt-binary.stl
gym_ignition_models-1.1.1.dist-info/LICENSE
gym_ignition_models-1.1.1.dist-info/METADATA
gym_ignition_models-1.1.1.dist-info/WHEEL
gym_ignition_models-1.1.1.dist-info/top_level.txt
gym_ignition_models-1.1.1.dist-info/RECORD
