Metadata-Version: 2.1
Name: gym-ignition-models
Version: 1.1.1
Summary: Collection of robot models for the Ignition Gazebo simulator.
Home-page: https://github.com/robotology/gym-ignition-models
Author: Diego Ferigo
Author-email: dgferigo@gmail.com
License: LGPL
Project-URL: Changelog, https://github.com/robotology/gym-ignition-models/releases
Project-URL: Tracker, https://github.com/robotology/gym-ignition-models/issues
Project-URL: Source, https://github.com/robotology/gym-ignition-models
Keywords: model,description,urdf,sdf,gazebo,ignition,robot,robotics,panda,icub,simulation
Platform: any
Classifier: Development Status :: 5 - Production/Stable
Classifier: Operating System :: POSIX :: Linux
Classifier: Topic :: Games/Entertainment :: Simulation
Classifier: Topic :: Scientific/Engineering :: Physics
Classifier: Framework :: Robot Framework
Classifier: Intended Audience :: Developers
Classifier: Intended Audience :: Science/Research
Classifier: Programming Language :: Python :: 3
Classifier: Programming Language :: Python :: 3 :: Only
Classifier: Programming Language :: Python :: 3.7
Classifier: Programming Language :: Python :: 3.8
Classifier: Programming Language :: Python :: 3.9
Classifier: Programming Language :: Python :: 3.10
Classifier: Programming Language :: Python :: Implementation :: CPython
Classifier: License :: OSI Approved :: GNU Lesser General Public License v2 or later (LGPLv2+)
Requires-Python: >=3.7
License-File: LICENSE
